{"name":"test","id":"test;test","testSteps":[{"number":1,"description":"1: test ({login\u003d\"lexa.pan2014@gmail.com\", password\u003d\"01122000\"})","duration":12149,"startTime":"2021-12-04T20:05:22.275+02:00[Europe/Helsinki]","screenshots":[{"screenshot":"0c7971a8b3470b8b8b6ca6514b178730bd1e4fbbdb6eec691ac3b84c77d3eee1.png","timeStamp":1638641134424}],"result":"SUCCESS","precondition":false,"level":0,"lineNumber":14,"children":[{"number":2,"description":"Given go to page","duration":8205,"startTime":"2021-12-04T20:05:22.308+02:00[Europe/Helsinki]","screenshots":[{"screenshot":"3a12ab47c339eaa651bd30956d8dcc4715f00ab9b90ab0c46793d337ba7d996b.png","timeStamp":1638641130513}],"result":"SUCCESS","precondition":false,"level":1},{"number":3,"description":"When step1","duration":2052,"startTime":"2021-12-04T20:05:30.522+02:00[Europe/Helsinki]","screenshots":[{"screenshot":"3a12ab47c339eaa651bd30956d8dcc4715f00ab9b90ab0c46793d337ba7d996b.png","timeStamp":1638641130524},{"screenshot":"8e08f5d21710c91b532c81ca9a03d9d7ea8a4f0960f64b8a2e6a07f0b6bacff7.png","timeStamp":1638641132574}],"result":"SUCCESS","precondition":false,"level":1},{"number":4,"description":"Then enter \"lexa.pan2014@gmail.com\" and \"01122000\"","duration":300,"startTime":"2021-12-04T20:05:32.575+02:00[Europe/Helsinki]","screenshots":[{"screenshot":"8e08f5d21710c91b532c81ca9a03d9d7ea8a4f0960f64b8a2e6a07f0b6bacff7.png","timeStamp":1638641132577},{"screenshot":"9c200667a519c59a5b48ffa1f2dfec7559a0cb1001acdfd13507a05198950528.png","timeStamp":1638641132875}],"result":"SUCCESS","precondition":false,"level":1},{"number":5,"description":"And step2","duration":1498,"startTime":"2021-12-04T20:05:32.877+02:00[Europe/Helsinki]","screenshots":[{"screenshot":"9c200667a519c59a5b48ffa1f2dfec7559a0cb1001acdfd13507a05198950528.png","timeStamp":1638641132879},{"screenshot":"0c7971a8b3470b8b8b6ca6514b178730bd1e4fbbdb6eec691ac3b84c77d3eee1.png","timeStamp":1638641134375}],"result":"SUCCESS","precondition":false,"level":1},{"number":6,"description":"Then next page loaded","duration":42,"startTime":"2021-12-04T20:05:34.377+02:00[Europe/Helsinki]","screenshots":[{"screenshot":"0c7971a8b3470b8b8b6ca6514b178730bd1e4fbbdb6eec691ac3b84c77d3eee1.png","timeStamp":1638641134378},{"screenshot":"0c7971a8b3470b8b8b6ca6514b178730bd1e4fbbdb6eec691ac3b84c77d3eee1.png","timeStamp":1638641134419}],"result":"SUCCESS","precondition":false,"level":1}]}],"userStory":{"id":"test","storyName":"test","displayName":"test","path":"Feature1.feature","type":"feature"},"featureTag":{"name":"test","type":"feature","displayName":"test"},"title":"Test","description":"","tags":[{"name":"test","type":"feature","displayName":"test"}],"startTime":"2021-12-04T20:05:22.212+02:00[Europe/Helsinki]","duration":12862,"projectKey":"","driver":"chrome","isManualTestingUpToDate":false,"dataTable":{"headers":["login","password"],"rows":[{"values":["\"lexa.pan2014@gmail.com\"","\"01122000\""],"lineNumber":14,"result":"SUCCESS"}],"predefinedRows":true,"scenarioOutline":"Given go to page\n\rWhen step1\n\rThen enter \u003clogin\u003e and \u003cpassword\u003e\n\rAnd step2\n\rThen next page loaded\n\r","dataSetDescriptors":[{"startRow":0,"rowCount":0,"name":"","description":""}]},"manual":false,"testSource":"Cucumber","result":"SUCCESS","scenarioOutline":"Given go to page\r\nWhen step1\r\nThen enter \u003clogin\u003e and \u003cpassword\u003e\r\nAnd step2\r\nThen next page loaded"}